lynxius/__init__.py
lynxius/client.py
lynxius_webapp-0.0.0.dist-info/LICENSE.md
lynxius_webapp-0.0.0.dist-info/METADATA
lynxius_webapp-0.0.0.dist-info/WHEEL
lynxius_webapp-0.0.0.dist-info/entry_points.txt
lynxius_webapp-0.0.0.dist-info/top_level.txt
lynxius_webapp-0.0.0.dist-info/RECORD
