Metadata-Version: 2.1
Name: lynxius-webapp
Version: 0.0.0
Summary: AI Observability & Evaluation - Evaluate, troubleshoot, and test your LLM models online and offline.
Home-page: https://github.com/lynxius/lynxius-python
Author: Lynxius Inc.
Author-email: contact@lynxius.ai
Keywords: lynxius
Classifier: Development Status :: 1 - Planning
Classifier: Intended Audience :: Developers
Classifier: Natural Language :: English
Classifier: Programming Language :: Python :: 3.12
Requires-Python: >=3.6
License-File: LICENSE.md
